LICENSE
MANIFEST.in
README.md
pyproject.toml
requirements.txt
setup.py
./bindings/hnsw_bindings.cpp
./bindings/pq_bindings.cpp
addons/__init__.py
addons/merger.py
bindings/pq_bindings.pyx
include/hnswlib/bruteforce.h
include/hnswlib/fusefilter.h
include/hnswlib/hnswalg.h
include/hnswlib/hnswlib.h
include/hnswlib/space_ip.h
include/hnswlib/space_l2.h
include/hnswlib/visited_list_pool.h
pqlite/__init__.py
pqlite/container.py
pqlite/enums.py
pqlite/filter.py
pqlite/helper.py
pqlite/index.py
pqlite/math.py
pqlite/profile.py
pqlite/utils.py
pqlite.egg-info/PKG-INFO
pqlite.egg-info/SOURCES.txt
pqlite.egg-info/dependency_links.txt
pqlite.egg-info/not-zip-safe
pqlite.egg-info/requires.txt
pqlite.egg-info/top_level.txt
pqlite/core/__init__.py
pqlite/core/codec/__init__.py
pqlite/core/codec/base.py
pqlite/core/codec/pq.py
pqlite/core/codec/vq.py
pqlite/core/index/__init__.py
pqlite/core/index/base.py
pqlite/core/index/flat_index.py
pqlite/core/index/pq_index.py
pqlite/core/index/hnsw/__init__.py
pqlite/core/index/hnsw/index.py
pqlite/storage/__init__.py
pqlite/storage/base.py
pqlite/storage/kv.py
pqlite/storage/table.py