Metadata-Version: 2.1
Name: pqlite
Version: 0.2.4
Summary: Fast and Light Approximate Nearest Neighbor Search Database integrated with the Jina Ecosystem
Home-page: https://github.com/jinaai/pqlite
Download-URL: https://github.com/jinaai/pqlite/tags
Author: Jina AI
Author-email: team@jina.ai
License: Apache License 2.0
Keywords: product-quantization approximate-nearest-neighbor
Platform: UNKNOWN
Classifier: Intended Audience :: Developers
Classifier: Intended Audience :: Science/Research
Classifier: License :: OSI Approved :: Apache Software License
Classifier: Operating System :: OS Independent
Classifier: Programming Language :: Python :: 3.7
Classifier: Programming Language :: Python :: 3.8
Classifier: Programming Language :: Python :: 3.9
Classifier: Topic :: Scientific/Engineering :: Artificial Intelligence
Requires-Python: >=3.7
Provides-Extra: testing
License-File: LICENSE
